{
  "description": "Glanceable cluster health overview \u2014 node status, pod phases, container restarts, and ArgoCD sync health",
  "layout": [
    {
      "h": 1,
      "i": "row-glance",
      "maxH": 1,
      "minH": 1,
      "minW": 12,
      "moved": false,
      "static": false,
      "w": 12,
      "x": 0,
      "y": 0
    },
    {
      "h": 4,
      "i": "stat-nodes-ready",
      "moved": false,
      "static": false,
      "w": 3,
      "x": 0,
      "y": 1
    },
    {
      "h": 4,
      "i": "stat-pods-running",
      "moved": false,
      "static": false,
      "w": 3,
      "x": 3,
      "y": 1
    },
    {
      "h": 4,
      "i": "stat-pods-failed",
      "moved": false,
      "static": false,
      "w": 3,
      "x": 6,
      "y": 1
    },
    {
      "h": 4,
      "i": "stat-apps-outofsync",
      "moved": false,
      "static": false,
      "w": 3,
      "x": 9,
      "y": 1
    },
    {
      "h": 1,
      "i": "row-workload",
      "maxH": 1,
      "minH": 1,
      "minW": 12,
      "moved": false,
      "static": false,
      "w": 12,
      "x": 0,
      "y": 5
    },
    {
      "h": 7,
      "i": "graph-pod-phases",
      "moved": false,
      "static": false,
      "w": 6,
      "x": 0,
      "y": 6
    },
    {
      "h": 7,
      "i": "graph-container-restarts",
      "moved": false,
      "static": false,
      "w": 6,
      "x": 6,
      "y": 6
    },
    {
      "h": 1,
      "i": "row-nodes",
      "maxH": 1,
      "minH": 1,
      "minW": 12,
      "moved": false,
      "static": false,
      "w": 12,
      "x": 0,
      "y": 13
    },
    {
      "h": 6,
      "i": "graph-node-ready",
      "moved": false,
      "static": false,
      "w": 12,
      "x": 0,
      "y": 14
    },
    {
      "h": 1,
      "i": "row-argocd",
      "maxH": 1,
      "minH": 1,
      "minW": 12,
      "moved": false,
      "static": false,
      "w": 12,
      "x": 0,
      "y": 20
    },
    {
      "h": 6,
      "i": "graph-argocd-sync",
      "moved": false,
      "static": false,
      "w": 6,
      "x": 0,
      "y": 21
    },
    {
      "h": 6,
      "i": "graph-argocd-health",
      "moved": false,
      "static": false,
      "w": 6,
      "x": 6,
      "y": 21
    }
  ],
  "panelMap": {},
  "tags": [
    "gitops"
  ],
  "title": "Cluster Health Overview",
  "uploadedGrafana": false,
  "variables": {
    "c80e3b31-d5cf-4cdf-9552-cf5e7c377102": {
      "allSelected": false,
      "customValue": "",
      "description": "Name of the cluster",
      "id": "c80e3b31-d5cf-4cdf-9552-cf5e7c377102",
      "key": "c80e3b31-d5cf-4cdf-9552-cf5e7c377102",
      "modificationUUID": "2193247a-83fc-493f-9e9c-eaf9305f2457",
      "multiSelect": false,
      "name": "k8s.cluster.name",
      "order": 0,
      "queryValue": "SELECT JSONExtractString(labels, 'k8s.cluster.name') AS `k8s.cluster.name` FROM signoz_metrics.distributed_time_series_v4_1day WHERE `metric_name` = 'k8s.node.cpu.time' GROUP BY `k8s.cluster.name`",
      "showALLOption": false,
      "sort": "DISABLED",
      "textboxValue": "",
      "type": "QUERY"
    }
  },
  "version": "v5",
  "widgets": [
    {
      "contextLinks": {
        "linksData": []
      },
      "id": "row-glance",
      "panelTypes": "row",
      "query": {
        "builder": {
          "queryData": [],
          "queryFormulas": []
        },
        "clickhouse_sql": [
          {
            "disabled": false,
            "legend": "",
            "name": "A",
            "query": ""
          }
        ],
        "promql": [
          {
            "disabled": false,
            "legend": "",
            "name": "A",
            "query": ""
          }
        ],
        "queryType": "builder"
      },
      "selectedLogFields": [],
      "selectedTracesFields": [],
      "thresholds": [],
      "title": "At a Glance"
    },
    {
      "bucketCount": 30,
      "bucketWidth": 0,
      "columnUnits": {},
      "description": "Nodes in Ready state",
      "fillSpans": false,
      "id": "stat-nodes-ready",
      "isStacked": false,
      "mergeAllActiveQueries": false,
      "nullZeroValues": "zero",
      "opacity": "1",
      "panelTypes": "value",
      "selectedLogFields": [
        {
          "dataType": "string",
          "name": "body",
          "type": ""
        },
        {
          "dataType": "string",
          "name": "timestamp",
          "type": ""
        }
      ],
      "selectedTracesFields": [
        {
          "dataType": "string",
          "id": "serviceName--string--tag--true",
          "isColumn": true,
          "isJSON": false,
          "key": "serviceName",
          "type": "tag"
        },
        {
          "dataType": "string",
          "id": "name--string--tag--true",
          "isColumn": true,
          "isJSON": false,
          "key": "name",
          "type": "tag"
        },
        {
          "dataType": "float64",
          "id": "durationNano--float64--tag--true",
          "isColumn": true,
          "isJSON": false,
          "key": "durationNano",
          "type": "tag"
        },
        {
          "dataType": "string",
          "id": "httpMethod--string--tag--true",
          "isColumn": true,
          "isJSON": false,
          "key": "httpMethod",
          "type": "tag"
        },
        {
          "dataType": "string",
          "id": "responseStatusCode--string--tag--true",
          "isColumn": true,
          "isJSON": false,
          "key": "responseStatusCode",
          "type": "tag"
        }
      ],
      "softMax": 0,
      "softMin": 0,
      "stackedBarChart": false,
      "timePreferance": "GLOBAL_TIME",
      "title": "Nodes Ready",
      "yAxisUnit": "none",
      "thresholds": [
        {
          "index": "c4b9c581-4052-4248-8f38-8d3b04fa92a5",
          "isEditEnabled": false,
          "keyIndex": 0,
          "selectedGraph": "value",
          "thresholdColor": "Green",
          "thresholdFormat": "Text",
          "thresholdLabel": "",
          "thresholdOperator": ">",
          "thresholdTableOptions": "A",
          "thresholdUnit": "none",
          "thresholdValue": 0
        }
      ],
      "query": {
        "builder": {
          "queryData": [
            {
              "aggregations": [
                {
                  "metricName": "k8s.node.condition_ready",
                  "reduceTo": "last",
                  "spaceAggregation": "sum",
                  "temporality": null,
                  "timeAggregation": "latest"
                }
              ],
              "dataSource": "metrics",
              "disabled": false,
              "expression": "A",
              "filter": {
                "expression": "k8s.cluster.name = $k8s.cluster.name"
              },
              "functions": [],
              "groupBy": [],
              "having": {
                "expression": ""
              },
              "legend": "",
              "limit": null,
              "orderBy": [],
              "queryName": "A",
              "stepInterval": null
            }
          ],
          "queryFormulas": []
        },
        "clickhouse_sql": [
          {
            "disabled": false,
            "legend": "",
            "name": "A",
            "query": ""
          }
        ],
        "id": "bc631dd2-5c33-4321-a197-24d351cce22c",
        "promql": [
          {
            "disabled": false,
            "legend": "",
            "name": "A",
            "query": ""
          }
        ],
        "queryType": "builder"
      }
    },
    {
      "bucketCount": 30,
      "bucketWidth": 0,
      "columnUnits": {},
      "description": "Pods currently in Running phase",
      "fillSpans": false,
      "id": "stat-pods-running",
      "isStacked": false,
      "mergeAllActiveQueries": false,
      "nullZeroValues": "zero",
      "opacity": "1",
      "panelTypes": "value",
      "selectedLogFields": [
        {
          "dataType": "string",
          "name": "body",
          "type": ""
        },
        {
          "dataType": "string",
          "name": "timestamp",
          "type": ""
        }
      ],
      "selectedTracesFields": [
        {
          "dataType": "string",
          "id": "serviceName--string--tag--true",
          "isColumn": true,
          "isJSON": false,
          "key": "serviceName",
          "type": "tag"
        },
        {
          "dataType": "string",
          "id": "name--string--tag--true",
          "isColumn": true,
          "isJSON": false,
          "key": "name",
          "type": "tag"
        },
        {
          "dataType": "float64",
          "id": "durationNano--float64--tag--true",
          "isColumn": true,
          "isJSON": false,
          "key": "durationNano",
          "type": "tag"
        },
        {
          "dataType": "string",
          "id": "httpMethod--string--tag--true",
          "isColumn": true,
          "isJSON": false,
          "key": "httpMethod",
          "type": "tag"
        },
        {
          "dataType": "string",
          "id": "responseStatusCode--string--tag--true",
          "isColumn": true,
          "isJSON": false,
          "key": "responseStatusCode",
          "type": "tag"
        }
      ],
      "softMax": 0,
      "softMin": 0,
      "stackedBarChart": false,
      "timePreferance": "GLOBAL_TIME",
      "title": "Running Pods",
      "yAxisUnit": "none",
      "thresholds": [
        {
          "index": "95e67d80-53b6-4094-8328-7b741e79ee97",
          "isEditEnabled": false,
          "keyIndex": 0,
          "selectedGraph": "value",
          "thresholdColor": "Blue",
          "thresholdFormat": "Text",
          "thresholdLabel": "",
          "thresholdOperator": ">",
          "thresholdTableOptions": "A",
          "thresholdUnit": "none",
          "thresholdValue": 0
        }
      ],
      "query": {
        "builder": {
          "queryData": [
            {
              "aggregations": [
                {
                  "metricName": "kube_pod_status_phase",
                  "reduceTo": "last",
                  "spaceAggregation": "sum",
                  "temporality": null,
                  "timeAggregation": "latest"
                }
              ],
              "dataSource": "metrics",
              "disabled": false,
              "expression": "A",
              "filter": {
                "expression": "phase = 'Running'"
              },
              "functions": [],
              "groupBy": [],
              "having": {
                "expression": ""
              },
              "legend": "",
              "limit": null,
              "orderBy": [],
              "queryName": "A",
              "stepInterval": null
            }
          ],
          "queryFormulas": []
        },
        "clickhouse_sql": [
          {
            "disabled": false,
            "legend": "",
            "name": "A",
            "query": ""
          }
        ],
        "id": "86ad6062-b866-4fcb-a366-d338185aba51",
        "promql": [
          {
            "disabled": false,
            "legend": "",
            "name": "A",
            "query": ""
          }
        ],
        "queryType": "builder"
      }
    },
    {
      "bucketCount": 30,
      "bucketWidth": 0,
      "columnUnits": {},
      "description": "Pods in Failed phase",
      "fillSpans": false,
      "id": "stat-pods-failed",
      "isStacked": false,
      "mergeAllActiveQueries": false,
      "nullZeroValues": "zero",
      "opacity": "1",
      "panelTypes": "value",
      "selectedLogFields": [
        {
          "dataType": "string",
          "name": "body",
          "type": ""
        },
        {
          "dataType": "string",
          "name": "timestamp",
          "type": ""
        }
      ],
      "selectedTracesFields": [
        {
          "dataType": "string",
          "id": "serviceName--string--tag--true",
          "isColumn": true,
          "isJSON": false,
          "key": "serviceName",
          "type": "tag"
        },
        {
          "dataType": "string",
          "id": "name--string--tag--true",
          "isColumn": true,
          "isJSON": false,
          "key": "name",
          "type": "tag"
        },
        {
          "dataType": "float64",
          "id": "durationNano--float64--tag--true",
          "isColumn": true,
          "isJSON": false,
          "key": "durationNano",
          "type": "tag"
        },
        {
          "dataType": "string",
          "id": "httpMethod--string--tag--true",
          "isColumn": true,
          "isJSON": false,
          "key": "httpMethod",
          "type": "tag"
        },
        {
          "dataType": "string",
          "id": "responseStatusCode--string--tag--true",
          "isColumn": true,
          "isJSON": false,
          "key": "responseStatusCode",
          "type": "tag"
        }
      ],
      "softMax": 0,
      "softMin": 0,
      "stackedBarChart": false,
      "timePreferance": "GLOBAL_TIME",
      "title": "Failed Pods",
      "yAxisUnit": "none",
      "thresholds": [
        {
          "index": "53d3e105-00cf-44dd-b3ff-839bfec9fbbe",
          "isEditEnabled": false,
          "keyIndex": 0,
          "selectedGraph": "value",
          "thresholdColor": "Red",
          "thresholdFormat": "Text",
          "thresholdLabel": "",
          "thresholdOperator": ">",
          "thresholdTableOptions": "A",
          "thresholdUnit": "none",
          "thresholdValue": 0
        }
      ],
      "query": {
        "builder": {
          "queryData": [
            {
              "aggregations": [
                {
                  "metricName": "kube_pod_status_phase",
                  "reduceTo": "last",
                  "spaceAggregation": "sum",
                  "temporality": null,
                  "timeAggregation": "latest"
                }
              ],
              "dataSource": "metrics",
              "disabled": false,
              "expression": "A",
              "filter": {
                "expression": "phase = 'Failed'"
              },
              "functions": [],
              "groupBy": [],
              "having": {
                "expression": ""
              },
              "legend": "",
              "limit": null,
              "orderBy": [],
              "queryName": "A",
              "stepInterval": null
            }
          ],
          "queryFormulas": []
        },
        "clickhouse_sql": [
          {
            "disabled": false,
            "legend": "",
            "name": "A",
            "query": ""
          }
        ],
        "id": "2d779ac1-5986-46c5-bb5f-fbef09805bda",
        "promql": [
          {
            "disabled": false,
            "legend": "",
            "name": "A",
            "query": ""
          }
        ],
        "queryType": "builder"
      }
    },
    {
      "bucketCount": 30,
      "bucketWidth": 0,
      "columnUnits": {},
      "description": "ArgoCD applications not in Synced state",
      "fillSpans": false,
      "id": "stat-apps-outofsync",
      "isStacked": false,
      "mergeAllActiveQueries": false,
      "nullZeroValues": "zero",
      "opacity": "1",
      "panelTypes": "value",
      "selectedLogFields": [
        {
          "dataType": "string",
          "name": "body",
          "type": ""
        },
        {
          "dataType": "string",
          "name": "timestamp",
          "type": ""
        }
      ],
      "selectedTracesFields": [
        {
          "dataType": "string",
          "id": "serviceName--string--tag--true",
          "isColumn": true,
          "isJSON": false,
          "key": "serviceName",
          "type": "tag"
        },
        {
          "dataType": "string",
          "id": "name--string--tag--true",
          "isColumn": true,
          "isJSON": false,
          "key": "name",
          "type": "tag"
        },
        {
          "dataType": "float64",
          "id": "durationNano--float64--tag--true",
          "isColumn": true,
          "isJSON": false,
          "key": "durationNano",
          "type": "tag"
        },
        {
          "dataType": "string",
          "id": "httpMethod--string--tag--true",
          "isColumn": true,
          "isJSON": false,
          "key": "httpMethod",
          "type": "tag"
        },
        {
          "dataType": "string",
          "id": "responseStatusCode--string--tag--true",
          "isColumn": true,
          "isJSON": false,
          "key": "responseStatusCode",
          "type": "tag"
        }
      ],
      "softMax": 0,
      "softMin": 0,
      "stackedBarChart": false,
      "timePreferance": "GLOBAL_TIME",
      "title": "Apps Out of Sync",
      "yAxisUnit": "none",
      "thresholds": [
        {
          "index": "46916479-8fbd-415a-a3fe-ef644a888c78",
          "isEditEnabled": false,
          "keyIndex": 0,
          "selectedGraph": "value",
          "thresholdColor": "Yellow",
          "thresholdFormat": "Text",
          "thresholdLabel": "",
          "thresholdOperator": ">",
          "thresholdTableOptions": "A",
          "thresholdUnit": "none",
          "thresholdValue": 0
        }
      ],
      "query": {
        "builder": {
          "queryData": [
            {
              "aggregations": [
                {
                  "metricName": "argocd_app_info",
                  "reduceTo": "last",
                  "spaceAggregation": "sum",
                  "temporality": null,
                  "timeAggregation": "latest"
                }
              ],
              "dataSource": "metrics",
              "disabled": false,
              "expression": "A",
              "filter": {
                "expression": "sync_status = 'OutOfSync'"
              },
              "functions": [],
              "groupBy": [],
              "having": {
                "expression": ""
              },
              "legend": "",
              "limit": null,
              "orderBy": [],
              "queryName": "A",
              "stepInterval": null
            }
          ],
          "queryFormulas": []
        },
        "clickhouse_sql": [
          {
            "disabled": false,
            "legend": "",
            "name": "A",
            "query": ""
          }
        ],
        "id": "d5120391-517d-45c0-9b89-e579fe26ffbb",
        "promql": [
          {
            "disabled": false,
            "legend": "",
            "name": "A",
            "query": ""
          }
        ],
        "queryType": "builder"
      }
    },
    {
      "contextLinks": {
        "linksData": []
      },
      "id": "row-workload",
      "panelTypes": "row",
      "query": {
        "builder": {
          "queryData": [],
          "queryFormulas": []
        },
        "clickhouse_sql": [
          {
            "disabled": false,
            "legend": "",
            "name": "A",
            "query": ""
          }
        ],
        "promql": [
          {
            "disabled": false,
            "legend": "",
            "name": "A",
            "query": ""
          }
        ],
        "queryType": "builder"
      },
      "selectedLogFields": [],
      "selectedTracesFields": [],
      "thresholds": [],
      "title": "Workload Health"
    },
    {
      "bucketCount": 30,
      "bucketWidth": 0,
      "columnUnits": {},
      "description": "Count of pods in each phase over time",
      "fillSpans": false,
      "id": "graph-pod-phases",
      "isStacked": true,
      "mergeAllActiveQueries": false,
      "nullZeroValues": "zero",
      "opacity": "1",
      "panelTypes": "graph",
      "selectedLogFields": [
        {
          "dataType": "string",
          "name": "body",
          "type": ""
        },
        {
          "dataType": "string",
          "name": "timestamp",
          "type": ""
        }
      ],
      "selectedTracesFields": [
        {
          "dataType": "string",
          "id": "serviceName--string--tag--true",
          "isColumn": true,
          "isJSON": false,
          "key": "serviceName",
          "type": "tag"
        },
        {
          "dataType": "string",
          "id": "name--string--tag--true",
          "isColumn": true,
          "isJSON": false,
          "key": "name",
          "type": "tag"
        },
        {
          "dataType": "float64",
          "id": "durationNano--float64--tag--true",
          "isColumn": true,
          "isJSON": false,
          "key": "durationNano",
          "type": "tag"
        },
        {
          "dataType": "string",
          "id": "httpMethod--string--tag--true",
          "isColumn": true,
          "isJSON": false,
          "key": "httpMethod",
          "type": "tag"
        },
        {
          "dataType": "string",
          "id": "responseStatusCode--string--tag--true",
          "isColumn": true,
          "isJSON": false,
          "key": "responseStatusCode",
          "type": "tag"
        }
      ],
      "softMax": 0,
      "softMin": 0,
      "stackedBarChart": false,
      "timePreferance": "GLOBAL_TIME",
      "title": "Pod Phases",
      "yAxisUnit": "none",
      "thresholds": [],
      "query": {
        "builder": {
          "queryData": [
            {
              "aggregations": [
                {
                  "metricName": "kube_pod_status_phase",
                  "reduceTo": "avg",
                  "spaceAggregation": "sum",
                  "temporality": null,
                  "timeAggregation": "latest"
                }
              ],
              "dataSource": "metrics",
              "disabled": false,
              "expression": "A",
              "filter": {
                "expression": "phase = 'Running'"
              },
              "functions": [],
              "groupBy": [],
              "having": {
                "expression": ""
              },
              "legend": "Running",
              "limit": null,
              "orderBy": [],
              "queryName": "A",
              "stepInterval": null
            },
            {
              "aggregations": [
                {
                  "metricName": "kube_pod_status_phase",
                  "reduceTo": "avg",
                  "spaceAggregation": "sum",
                  "temporality": null,
                  "timeAggregation": "latest"
                }
              ],
              "dataSource": "metrics",
              "disabled": false,
              "expression": "B",
              "filter": {
                "expression": "phase = 'Pending'"
              },
              "functions": [],
              "groupBy": [],
              "having": {
                "expression": ""
              },
              "legend": "Pending",
              "limit": null,
              "orderBy": [],
              "queryName": "B",
              "stepInterval": null
            },
            {
              "aggregations": [
                {
                  "metricName": "kube_pod_status_phase",
                  "reduceTo": "avg",
                  "spaceAggregation": "sum",
                  "temporality": null,
                  "timeAggregation": "latest"
                }
              ],
              "dataSource": "metrics",
              "disabled": false,
              "expression": "C",
              "filter": {
                "expression": "phase = 'Failed'"
              },
              "functions": [],
              "groupBy": [],
              "having": {
                "expression": ""
              },
              "legend": "Failed",
              "limit": null,
              "orderBy": [],
              "queryName": "C",
              "stepInterval": null
            },
            {
              "aggregations": [
                {
                  "metricName": "kube_pod_status_phase",
                  "reduceTo": "avg",
                  "spaceAggregation": "sum",
                  "temporality": null,
                  "timeAggregation": "latest"
                }
              ],
              "dataSource": "metrics",
              "disabled": false,
              "expression": "D",
              "filter": {
                "expression": "phase = 'Unknown'"
              },
              "functions": [],
              "groupBy": [],
              "having": {
                "expression": ""
              },
              "legend": "Unknown",
              "limit": null,
              "orderBy": [],
              "queryName": "D",
              "stepInterval": null
            }
          ],
          "queryFormulas": []
        },
        "clickhouse_sql": [
          {
            "disabled": false,
            "legend": "",
            "name": "A",
            "query": ""
          }
        ],
        "id": "d126b522-81ec-4764-a445-ea03a7d509be",
        "promql": [
          {
            "disabled": false,
            "legend": "",
            "name": "A",
            "query": ""
          }
        ],
        "queryType": "builder"
      }
    },
    {
      "bucketCount": 30,
      "bucketWidth": 0,
      "columnUnits": {},
      "description": "Rate of container restarts \u2014 a rising trend indicates flapping workloads",
      "fillSpans": false,
      "id": "graph-container-restarts",
      "isStacked": false,
      "mergeAllActiveQueries": false,
      "nullZeroValues": "zero",
      "opacity": "1",
      "panelTypes": "graph",
      "selectedLogFields": [
        {
          "dataType": "string",
          "name": "body",
          "type": ""
        },
        {
          "dataType": "string",
          "name": "timestamp",
          "type": ""
        }
      ],
      "selectedTracesFields": [
        {
          "dataType": "string",
          "id": "serviceName--string--tag--true",
          "isColumn": true,
          "isJSON": false,
          "key": "serviceName",
          "type": "tag"
        },
        {
          "dataType": "string",
          "id": "name--string--tag--true",
          "isColumn": true,
          "isJSON": false,
          "key": "name",
          "type": "tag"
        },
        {
          "dataType": "float64",
          "id": "durationNano--float64--tag--true",
          "isColumn": true,
          "isJSON": false,
          "key": "durationNano",
          "type": "tag"
        },
        {
          "dataType": "string",
          "id": "httpMethod--string--tag--true",
          "isColumn": true,
          "isJSON": false,
          "key": "httpMethod",
          "type": "tag"
        },
        {
          "dataType": "string",
          "id": "responseStatusCode--string--tag--true",
          "isColumn": true,
          "isJSON": false,
          "key": "responseStatusCode",
          "type": "tag"
        }
      ],
      "softMax": 0,
      "softMin": 0,
      "stackedBarChart": false,
      "timePreferance": "GLOBAL_TIME",
      "title": "Container Restart Rate",
      "yAxisUnit": "none",
      "thresholds": [],
      "query": {
        "builder": {
          "queryData": [
            {
              "aggregations": [
                {
                  "metricName": "kube_pod_container_status_restarts_total",
                  "reduceTo": "avg",
                  "spaceAggregation": "sum",
                  "temporality": null,
                  "timeAggregation": "rate"
                }
              ],
              "dataSource": "metrics",
              "disabled": false,
              "expression": "A",
              "filter": {
                "expression": ""
              },
              "functions": [],
              "groupBy": [
                {
                  "dataType": "string",
                  "id": "namespace--string--tag--false",
                  "isColumn": false,
                  "isJSON": false,
                  "key": "namespace",
                  "type": "tag"
                }
              ],
              "having": {
                "expression": ""
              },
              "legend": "{{namespace}}",
              "limit": null,
              "orderBy": [],
              "queryName": "A",
              "stepInterval": null
            }
          ],
          "queryFormulas": []
        },
        "clickhouse_sql": [
          {
            "disabled": false,
            "legend": "",
            "name": "A",
            "query": ""
          }
        ],
        "id": "26ad68e6-73b7-4470-8ee3-f3ca8aa15064",
        "promql": [
          {
            "disabled": false,
            "legend": "",
            "name": "A",
            "query": ""
          }
        ],
        "queryType": "builder"
      }
    },
    {
      "contextLinks": {
        "linksData": []
      },
      "id": "row-nodes",
      "panelTypes": "row",
      "query": {
        "builder": {
          "queryData": [],
          "queryFormulas": []
        },
        "clickhouse_sql": [
          {
            "disabled": false,
            "legend": "",
            "name": "A",
            "query": ""
          }
        ],
        "promql": [
          {
            "disabled": false,
            "legend": "",
            "name": "A",
            "query": ""
          }
        ],
        "queryType": "builder"
      },
      "selectedLogFields": [],
      "selectedTracesFields": [],
      "thresholds": [],
      "title": "Node Health"
    },
    {
      "bucketCount": 30,
      "bucketWidth": 0,
      "columnUnits": {},
      "description": "Ready status per node (1=Ready, 0=Not Ready)",
      "fillSpans": false,
      "id": "graph-node-ready",
      "isStacked": false,
      "mergeAllActiveQueries": false,
      "nullZeroValues": "zero",
      "opacity": "1",
      "panelTypes": "graph",
      "selectedLogFields": [
        {
          "dataType": "string",
          "name": "body",
          "type": ""
        },
        {
          "dataType": "string",
          "name": "timestamp",
          "type": ""
        }
      ],
      "selectedTracesFields": [
        {
          "dataType": "string",
          "id": "serviceName--string--tag--true",
          "isColumn": true,
          "isJSON": false,
          "key": "serviceName",
          "type": "tag"
        },
        {
          "dataType": "string",
          "id": "name--string--tag--true",
          "isColumn": true,
          "isJSON": false,
          "key": "name",
          "type": "tag"
        },
        {
          "dataType": "float64",
          "id": "durationNano--float64--tag--true",
          "isColumn": true,
          "isJSON": false,
          "key": "durationNano",
          "type": "tag"
        },
        {
          "dataType": "string",
          "id": "httpMethod--string--tag--true",
          "isColumn": true,
          "isJSON": false,
          "key": "httpMethod",
          "type": "tag"
        },
        {
          "dataType": "string",
          "id": "responseStatusCode--string--tag--true",
          "isColumn": true,
          "isJSON": false,
          "key": "responseStatusCode",
          "type": "tag"
        }
      ],
      "softMax": 0,
      "softMin": 0,
      "stackedBarChart": false,
      "timePreferance": "GLOBAL_TIME",
      "title": "Node Readiness",
      "yAxisUnit": "none",
      "thresholds": [
        {
          "index": "bc56d146-6069-4b18-a973-2456815c36e9",
          "isEditEnabled": false,
          "keyIndex": 0,
          "selectedGraph": "graph",
          "thresholdColor": "Red",
          "thresholdFormat": "1",
          "thresholdLabel": "",
          "thresholdOperator": "<",
          "thresholdTableOptions": "A",
          "thresholdUnit": "none",
          "thresholdValue": 1
        }
      ],
      "query": {
        "builder": {
          "queryData": [
            {
              "aggregations": [
                {
                  "metricName": "k8s.node.condition_ready",
                  "reduceTo": "avg",
                  "spaceAggregation": "sum",
                  "temporality": null,
                  "timeAggregation": "latest"
                }
              ],
              "dataSource": "metrics",
              "disabled": false,
              "expression": "A",
              "filter": {
                "expression": "k8s.cluster.name = $k8s.cluster.name"
              },
              "functions": [],
              "groupBy": [
                {
                  "dataType": "string",
                  "id": "k8s.node.name--string--tag--false",
                  "isColumn": false,
                  "isJSON": false,
                  "key": "k8s.node.name",
                  "type": "tag"
                }
              ],
              "having": {
                "expression": ""
              },
              "legend": "{{k8s.node.name}}",
              "limit": null,
              "orderBy": [],
              "queryName": "A",
              "stepInterval": null
            }
          ],
          "queryFormulas": []
        },
        "clickhouse_sql": [
          {
            "disabled": false,
            "legend": "",
            "name": "A",
            "query": ""
          }
        ],
        "id": "e23f96b2-2da0-431f-9c22-48a3baf472b8",
        "promql": [
          {
            "disabled": false,
            "legend": "",
            "name": "A",
            "query": ""
          }
        ],
        "queryType": "builder"
      }
    },
    {
      "contextLinks": {
        "linksData": []
      },
      "id": "row-argocd",
      "panelTypes": "row",
      "query": {
        "builder": {
          "queryData": [],
          "queryFormulas": []
        },
        "clickhouse_sql": [
          {
            "disabled": false,
            "legend": "",
            "name": "A",
            "query": ""
          }
        ],
        "promql": [
          {
            "disabled": false,
            "legend": "",
            "name": "A",
            "query": ""
          }
        ],
        "queryType": "builder"
      },
      "selectedLogFields": [],
      "selectedTracesFields": [],
      "thresholds": [],
      "title": "ArgoCD"
    },
    {
      "bucketCount": 30,
      "bucketWidth": 0,
      "columnUnits": {},
      "description": "Count of apps by sync state over time",
      "fillSpans": false,
      "id": "graph-argocd-sync",
      "isStacked": false,
      "mergeAllActiveQueries": false,
      "nullZeroValues": "zero",
      "opacity": "1",
      "panelTypes": "graph",
      "selectedLogFields": [
        {
          "dataType": "string",
          "name": "body",
          "type": ""
        },
        {
          "dataType": "string",
          "name": "timestamp",
          "type": ""
        }
      ],
      "selectedTracesFields": [
        {
          "dataType": "string",
          "id": "serviceName--string--tag--true",
          "isColumn": true,
          "isJSON": false,
          "key": "serviceName",
          "type": "tag"
        },
        {
          "dataType": "string",
          "id": "name--string--tag--true",
          "isColumn": true,
          "isJSON": false,
          "key": "name",
          "type": "tag"
        },
        {
          "dataType": "float64",
          "id": "durationNano--float64--tag--true",
          "isColumn": true,
          "isJSON": false,
          "key": "durationNano",
          "type": "tag"
        },
        {
          "dataType": "string",
          "id": "httpMethod--string--tag--true",
          "isColumn": true,
          "isJSON": false,
          "key": "httpMethod",
          "type": "tag"
        },
        {
          "dataType": "string",
          "id": "responseStatusCode--string--tag--true",
          "isColumn": true,
          "isJSON": false,
          "key": "responseStatusCode",
          "type": "tag"
        }
      ],
      "softMax": 0,
      "softMin": 0,
      "stackedBarChart": false,
      "timePreferance": "GLOBAL_TIME",
      "title": "ArgoCD Sync Status",
      "yAxisUnit": "none",
      "thresholds": [],
      "query": {
        "builder": {
          "queryData": [
            {
              "aggregations": [
                {
                  "metricName": "argocd_app_info",
                  "reduceTo": "avg",
                  "spaceAggregation": "sum",
                  "temporality": null,
                  "timeAggregation": "latest"
                }
              ],
              "dataSource": "metrics",
              "disabled": false,
              "expression": "A",
              "filter": {
                "expression": "sync_status = 'Synced'"
              },
              "functions": [],
              "groupBy": [],
              "having": {
                "expression": ""
              },
              "legend": "Synced",
              "limit": null,
              "orderBy": [],
              "queryName": "A",
              "stepInterval": null
            },
            {
              "aggregations": [
                {
                  "metricName": "argocd_app_info",
                  "reduceTo": "avg",
                  "spaceAggregation": "sum",
                  "temporality": null,
                  "timeAggregation": "latest"
                }
              ],
              "dataSource": "metrics",
              "disabled": false,
              "expression": "B",
              "filter": {
                "expression": "sync_status = 'OutOfSync'"
              },
              "functions": [],
              "groupBy": [],
              "having": {
                "expression": ""
              },
              "legend": "Out of Sync",
              "limit": null,
              "orderBy": [],
              "queryName": "B",
              "stepInterval": null
            }
          ],
          "queryFormulas": []
        },
        "clickhouse_sql": [
          {
            "disabled": false,
            "legend": "",
            "name": "A",
            "query": ""
          }
        ],
        "id": "13acab8f-4568-4e0a-8ad8-fd508ad53c14",
        "promql": [
          {
            "disabled": false,
            "legend": "",
            "name": "A",
            "query": ""
          }
        ],
        "queryType": "builder"
      }
    },
    {
      "bucketCount": 30,
      "bucketWidth": 0,
      "columnUnits": {},
      "description": "Count of apps by health state over time",
      "fillSpans": false,
      "id": "graph-argocd-health",
      "isStacked": false,
      "mergeAllActiveQueries": false,
      "nullZeroValues": "zero",
      "opacity": "1",
      "panelTypes": "graph",
      "selectedLogFields": [
        {
          "dataType": "string",
          "name": "body",
          "type": ""
        },
        {
          "dataType": "string",
          "name": "timestamp",
          "type": ""
        }
      ],
      "selectedTracesFields": [
        {
          "dataType": "string",
          "id": "serviceName--string--tag--true",
          "isColumn": true,
          "isJSON": false,
          "key": "serviceName",
          "type": "tag"
        },
        {
          "dataType": "string",
          "id": "name--string--tag--true",
          "isColumn": true,
          "isJSON": false,
          "key": "name",
          "type": "tag"
        },
        {
          "dataType": "float64",
          "id": "durationNano--float64--tag--true",
          "isColumn": true,
          "isJSON": false,
          "key": "durationNano",
          "type": "tag"
        },
        {
          "dataType": "string",
          "id": "httpMethod--string--tag--true",
          "isColumn": true,
          "isJSON": false,
          "key": "httpMethod",
          "type": "tag"
        },
        {
          "dataType": "string",
          "id": "responseStatusCode--string--tag--true",
          "isColumn": true,
          "isJSON": false,
          "key": "responseStatusCode",
          "type": "tag"
        }
      ],
      "softMax": 0,
      "softMin": 0,
      "stackedBarChart": false,
      "timePreferance": "GLOBAL_TIME",
      "title": "ArgoCD App Health",
      "yAxisUnit": "none",
      "thresholds": [],
      "query": {
        "builder": {
          "queryData": [
            {
              "aggregations": [
                {
                  "metricName": "argocd_app_info",
                  "reduceTo": "avg",
                  "spaceAggregation": "sum",
                  "temporality": null,
                  "timeAggregation": "latest"
                }
              ],
              "dataSource": "metrics",
              "disabled": false,
              "expression": "A",
              "filter": {
                "expression": "health_status = 'Healthy'"
              },
              "functions": [],
              "groupBy": [],
              "having": {
                "expression": ""
              },
              "legend": "Healthy",
              "limit": null,
              "orderBy": [],
              "queryName": "A",
              "stepInterval": null
            },
            {
              "aggregations": [
                {
                  "metricName": "argocd_app_info",
                  "reduceTo": "avg",
                  "spaceAggregation": "sum",
                  "temporality": null,
                  "timeAggregation": "latest"
                }
              ],
              "dataSource": "metrics",
              "disabled": false,
              "expression": "B",
              "filter": {
                "expression": "health_status = 'Degraded'"
              },
              "functions": [],
              "groupBy": [],
              "having": {
                "expression": ""
              },
              "legend": "Degraded",
              "limit": null,
              "orderBy": [],
              "queryName": "B",
              "stepInterval": null
            },
            {
              "aggregations": [
                {
                  "metricName": "argocd_app_info",
                  "reduceTo": "avg",
                  "spaceAggregation": "sum",
                  "temporality": null,
                  "timeAggregation": "latest"
                }
              ],
              "dataSource": "metrics",
              "disabled": false,
              "expression": "C",
              "filter": {
                "expression": "health_status = 'Progressing'"
              },
              "functions": [],
              "groupBy": [],
              "having": {
                "expression": ""
              },
              "legend": "Progressing",
              "limit": null,
              "orderBy": [],
              "queryName": "C",
              "stepInterval": null
            },
            {
              "aggregations": [
                {
                  "metricName": "argocd_app_info",
                  "reduceTo": "avg",
                  "spaceAggregation": "sum",
                  "temporality": null,
                  "timeAggregation": "latest"
                }
              ],
              "dataSource": "metrics",
              "disabled": false,
              "expression": "D",
              "filter": {
                "expression": "health_status = 'Missing'"
              },
              "functions": [],
              "groupBy": [],
              "having": {
                "expression": ""
              },
              "legend": "Missing",
              "limit": null,
              "orderBy": [],
              "queryName": "D",
              "stepInterval": null
            }
          ],
          "queryFormulas": []
        },
        "clickhouse_sql": [
          {
            "disabled": false,
            "legend": "",
            "name": "A",
            "query": ""
          }
        ],
        "id": "6caf5764-b852-4f80-8645-906e0dcbbe14",
        "promql": [
          {
            "disabled": false,
            "legend": "",
            "name": "A",
            "query": ""
          }
        ],
        "queryType": "builder"
      }
    }
  ]
}
